[1,["1b7d308ae@6c48a"],["_textureSource"],["cc.SpriteFrame"],0,[[[{"name":"Countdown_02","rect":{"x":3,"y":685,"width":282,"height":332},"offset":{"x":0,"y":0},"originalSize":{"width":282,"height":332},"rotated":false,"capInsets":[0,0,0,0],"packable":true}],[0],0,[0],[0],[0]],[[{"name":"Game_start_bg02","rect":{"x":3,"y":29,"width":651,"height":650},"offset":{"x":0,"y":0},"originalSize":{"width":651,"height":650},"rotated":false,"capInsets":[0,0,0,0],"packable":true}],[0],0,[0],[0],[0]],[[{"name":"Game_sign_word","rect":{"x":683,"y":3,"width":333,"height":27},"offset":{"x":0,"y":0},"originalSize":{"width":333,"height":27},"rotated":false,"capInsets":[0,0,0,0],"packable":true}],[0],0,[0],[0],[0]],[[{"name":"Loading_Image_2","rect":{"x":660,"y":36,"width":324,"height":352},"offset":{"x":0,"y":0},"originalSize":{"width":324,"height":352},"rotated":true,"capInsets":[0,0,0,0],"packable":true}],[0],0,[0],[0],[0]],[[{"name":"toastBg","rect":{"x":3,"y":3,"width":674,"height":20},"offset":{"x":0,"y":0},"originalSize":{"width":674,"height":20},"rotated":false,"capInsets":[0,0,0,0],"packable":true}],[0],0,[0],[0],[0]],[[{"name":"Loading_Image_1","rect":{"x":660,"y":366,"width":324,"height":352},"offset":{"x":0,"y":0},"originalSize":{"width":324,"height":352},"rotated":true,"capInsets":[0,0,0,0],"packable":true}],[0],0,[0],[0],[0]],[[{"name":"Loading_Image_3","rect":{"x":291,"y":696,"width":324,"height":352},"offset":{"x":0,"y":0},"originalSize":{"width":324,"height":352},"rotated":true,"capInsets":[0,0,0,0],"packable":true}],[0],0,[0],[0],[0]],[[{"name":"Loading_Image_4","rect":{"x":649,"y":696,"width":324,"height":352},"offset":{"x":0,"y":0},"originalSize":{"width":324,"height":352},"rotated":true,"capInsets":[0,0,0,0],"packable":true}],[0],0,[0],[0],[0]]]]
